CHANGELOG.txt
LICENSE.txt
MANIFEST.in
README.md
setup.py
MeaxisNetwork.egg-info/PKG-INFO
MeaxisNetwork.egg-info/SOURCES.txt
MeaxisNetwork.egg-info/dependency_links.txt
MeaxisNetwork.egg-info/requires.txt
MeaxisNetwork.egg-info/top_level.txt
meaxisnetwork/__init__.py
meaxisnetwork/accounts.py
meaxisnetwork/creations.py
meaxisnetwork/credentials.py
meaxisnetwork/shop.py
meaxisnetwork/users.py
meaxisnetwork/utils.py
meaxisnetwork/vote.py
meaxisnetwork/examples/__init__.py
meaxisnetwork/examples/userExample.py
meaxisnetwork/v2/__init__.py
meaxisnetwork/v2/funfact.py