Metadata-Version: 2.1
Name: MeaxisNetwork
Version: 0.1.5
Summary: A python wrapper for the MeaxisNetwork API.
Home-page: https://meaxisnetwork.net/create/docs/api/index
Author: MeaxisNetwork
Author-email: meaxis@meaxisnetwork.net
License: MIT
Keywords: meaxisnetwork
Platform: UNKNOWN
Classifier: Development Status :: 5 - Production/Stable
Classifier: Intended Audience :: Education
Classifier: Operating System :: Microsoft :: Windows :: Windows 10
Classifier: License :: OSI Approved :: MIT License
Classifier: Programming Language :: Python :: 3
